pyquickjoin-2.1.0.dist-info/licenses/AUTHORS.rst
quickjoin/__init__.py
quickjoin/main.py
pyquickjoin-2.1.0.dist-info/METADATA
pyquickjoin-2.1.0.dist-info/WHEEL
pyquickjoin-2.1.0.dist-info/entry_points.txt
pyquickjoin-2.1.0.dist-info/top_level.txt
pyquickjoin-2.1.0.dist-info/RECORD
