Metadata-Version: 2.4
Name: pyquickjoin
Version: 2.1.0
Summary: Quickly join two unsorted files
Home-page: https://gitlab.com/onlynone/pyquickjoin
Author: Steven Willis
Author-email: onlynone@gmail.com
License: BSD
Keywords: quickjoin
Classifier: Development Status :: 5 - Production/Stable
Classifier: Intended Audience :: Developers
Classifier: Intended Audience :: Information Technology
Classifier: Intended Audience :: Science/Research
Classifier: Intended Audience :: System Administrators
Classifier: License :: OSI Approved :: BSD License
Classifier: Natural Language :: English
Classifier: Programming Language :: Python :: 2
Classifier: Programming Language :: Python :: 2.6
Classifier: Programming Language :: Python :: 2.7
Classifier: Programming Language :: Python :: 3
License-File: AUTHORS.rst
Provides-Extra: bsddb3
Requires-Dist: bsddb3; extra == "bsddb3"
Provides-Extra: berkeleydb
Requires-Dist: berkeleydb; extra == "berkeleydb"
Dynamic: author
Dynamic: author-email
Dynamic: classifier
Dynamic: description
Dynamic: home-page
Dynamic: keywords
Dynamic: license
Dynamic: license-file
Dynamic: provides-extra
Dynamic: summary
